<?xml version="1.0" encoding="utf-8" ?>
<dwsync>
<file name="portlets.html" server="unix.ncl.ac.uk/public_html/" local="129961522860000000" remote="129961522860000000" />
<file name="connect-lists-through-tabs.html" server="unix.ncl.ac.uk/public_html/" local="129961522850000000" remote="129961522850000000" />
<file name="delay-start.html" server="unix.ncl.ac.uk/public_html/" local="129961522850000000" remote="129961522850000000" />
<file name="display-grid.html" server="unix.ncl.ac.uk/public_html/" local="129961522850000000" remote="129961522850000000" />
<file name="items.html" server="unix.ncl.ac.uk/public_html/" local="129961522850000000" remote="129961522850000000" />
<file name="empty-lists.html" server="unix.ncl.ac.uk/public_html/" local="129961522850000000" remote="129961522850000000" />
<file name="index.html" server="unix.ncl.ac.uk/public_html/" local="129961522850000000" remote="129961522850000000" />
<file name="default.html" server="unix.ncl.ac.uk/public_html/" local="129961522850000000" remote="129961522850000000" />
<file name="placeholder.html" server="unix.ncl.ac.uk/public_html/" local="129961522860000000" remote="129961522860000000" />
<file name="connect-lists.html" server="unix.ncl.ac.uk/public_html/" local="129961522850000000" remote="129961522850000000" />
</dwsync>